census_area/__init__.py
census_area/core.py
census_area/lodes.py
census_area/variables.py
census_area-0.4.6.dist-info/licenses/LICENSE.md
census_area-0.4.6.dist-info/METADATA
census_area-0.4.6.dist-info/WHEEL
census_area-0.4.6.dist-info/top_level.txt
census_area-0.4.6.dist-info/RECORD
