Metadata-Version: 2.4
Name: census_area
Version: 0.4.6
Summary: Census data for arbitrary geographies
Home-page: https://github.com/datamade/census_area
Author: Forest Gregg
Author-email: fgregg@datamade.us
Classifier: Development Status :: 4 - Beta
Classifier: Intended Audience :: Developers
Classifier: Intended Audience :: Science/Research
Classifier: License :: OSI Approved :: MIT License
Classifier: Natural Language :: English
Classifier: Operating System :: MacOS :: MacOS X
Classifier: Operating System :: Microsoft :: Windows
Classifier: Operating System :: POSIX
Classifier: Programming Language :: Python :: 3.5
Classifier: Topic :: Software Development :: Libraries :: Python Modules
Classifier: Topic :: Scientific/Engineering
Classifier: Topic :: Scientific/Engineering :: Information Analysis
License-File: LICENSE.md
Requires-Dist: esridump
Requires-Dist: census
Requires-Dist: shapely
Requires-Dist: pyshp
Requires-Dist: pyproj
Dynamic: author
Dynamic: author-email
Dynamic: classifier
Dynamic: description
Dynamic: home-page
Dynamic: license-file
Dynamic: requires-dist
Dynamic: summary
